luna_alimtalk/__init__.py
luna_alimtalk/luna.py
luna_alimtalk-0.1.0.dist-info/METADATA
luna_alimtalk-0.1.0.dist-info/WHEEL
luna_alimtalk-0.1.0.dist-info/RECORD
