Metadata-Version: 2.1
Name: luna-alimtalk
Version: 0.1.0
Summary: luna alimtalk api package
Home-page: https://github.com/jslim01/luna-alimtalk
Author: jslim01
Author-email: jslim@uniai.co.kr
Requires-Python: >=3.9,<4.0
Classifier: Programming Language :: Python :: 3
Classifier: Programming Language :: Python :: 3.9
Classifier: Programming Language :: Python :: 3.10
Classifier: Programming Language :: Python :: 3.11
Classifier: Programming Language :: Python :: 3.12
Classifier: Programming Language :: Python :: 3.13
Requires-Dist: httpx (>=0.28.1,<0.29.0)
Project-URL: Repository, https://github.com/jslim01/luna-alimtalk
